voluptuary
