Metadata-Version: 1.1
Name: voluptuary
Version: 0.0.2
Summary: convert json schemas to voluptuous schemas
Home-page: https://github.com/pglass/voluptuary
Author: Paul Glass
Author-email: pnglass@gmail.com
License: MIT
Keywords: convert schema json voluptuous
Platform: UNKNOWN
Classifier: Development Status :: 2 - Pre-Alpha
Classifier: Environment :: Console
Classifier: Intended Audience :: Developers
Classifier: License :: OSI Approved :: MIT License
Classifier: Operating System :: OS Independent
Classifier: Programming Language :: Python :: 3.5
Classifier: Programming Language :: Python :: 3.6
